yomilog/manage.py
yomilog/app/__init__.py
yomilog/app/apps.py
yomilog/app/models.py
yomilog/app/views.py
yomilog/app/management/__init__.py
yomilog/app/migrations/0001_initial.py
yomilog/app/migrations/__init__.py
yomilog/app/templates/app/index.html
yomilog/yomilog/__init__.py
yomilog/yomilog/asgi.py
yomilog/yomilog/settings.py
yomilog/yomilog/urls.py
yomilog/yomilog/wsgi.py
yomilog-1.0.0.dist-info/METADATA
yomilog-1.0.0.dist-info/WHEEL
yomilog-1.0.0.dist-info/top_level.txt
yomilog-1.0.0.dist-info/RECORD
