Metadata-Version: 2.1
Name: yomilog
Version: 1.0.0
Summary: The YomiLog web application.
Author-email: BeProud <project@beproud.jp>
License: BSD License
Keywords: web,yomilog
Classifier: Development Status :: 4 - Beta
Classifier: Framework :: Django
Classifier: License :: OSI Approved :: BSD License
Classifier: Programming Language :: Python
Classifier: Programming Language :: Python :: 3.11
Requires-Python: >=3.11
Requires-Dist: Django >=4.2
Requires-Dist: psycopg2 >=2.9
